django_select2/__init__.py
django_select2/_version.py
django_select2/apps.py
django_select2/cache.py
django_select2/conf.py
django_select2/forms.py
django_select2/urls.py
django_select2/views.py
django_select2/static/django_select2/django_select2.css
django_select2/static/django_select2/django_select2.js
django_select2-8.4.7.dist-info/licenses/LICENSE
django_select2-8.4.7.dist-info/WHEEL
django_select2-8.4.7.dist-info/METADATA
django_select2-8.4.7.dist-info/RECORD
