Metadata-Version: 2.4
Name: django-select2
Version: 8.4.7
Summary: This is a Django_ integration of Select2_.
Keywords: Django,select2,autocomplete,typeahead
Author-email: Johannes Maron <johannes@maron.family>
Requires-Python: >=3.10
Classifier: Development Status :: 5 - Production/Stable
Classifier: License :: OSI Approved :: MIT License
Classifier: Intended Audience :: Developers
Classifier: Environment :: Web Environment
Classifier: Operating System :: OS Independent
Classifier: Programming Language :: Python
Classifier: Programming Language :: Python :: 3
Classifier: Programming Language :: Python :: 3 :: Only
Classifier: Programming Language :: Python :: 3.10
Classifier: Programming Language :: Python :: 3.11
Classifier: Programming Language :: Python :: 3.12
Classifier: Programming Language :: Python :: 3.13
Classifier: Programming Language :: Python :: 3.14
Classifier: Framework :: Django
Classifier: Framework :: Django :: 4.2
Classifier: Framework :: Django :: 5.2
Classifier: Framework :: Django :: 6.0
Classifier: Topic :: Software Development
License-File: LICENSE
Requires-Dist: django>=4.2
Requires-Dist: django-appconf>=0.6.0
Project-URL: Changelog, https://github.com/codingjoe/django-select2/releases
Project-URL: Documentation, https://django-select2.rtfd.io/
Project-URL: Funding, https://github.com/sponsors/codingjoe
Project-URL: Homepage, https://github.com/codingjoe/django-select2
Project-URL: Issues, https://github.com/codingjoe/django-select2/issues
Project-URL: Releasenotes, https://github.com/codingjoe/django-select2/releases/latest
Project-URL: Source, https://github.com/codingjoe/django-select2
